{"slug":"have","name":"🇬🇧 Verb HAVE","meaning":"to possess, to experience","verb_forms":["have","has","had","having"],"phrases":{"ru":[{"origin":"У меня есть вопрос","target":"I have a question","tense":"Present"},{"origin":"У неё есть собака","target":"She has a dog","tense":"Present"},{"origin":"У них есть время","target":"They have time","tense":"Present"},{"origin":"У нас есть дом","target":"We have a house","tense":"Present"},{"origin":"У него есть машина","target":"He has a car","tense":"Present"},{"origin":"У меня есть идея","target":"I have an idea","tense":"Present"},{"origin":"У тебя есть деньги?","target":"Do you have money?","tense":"Present"},{"origin":"У нас нет выбора","target":"We don't have a choice","tense":"Present"},{"origin":"У неё есть работа","target":"She has a job","tense":"Present"},{"origin":"У них есть дети","target":"They have children","tense":"Present"},{"origin":"У меня был шанс","target":"I had a chance","tense":"Past Simple"},{"origin":"У нас была встреча","target":"We had a meeting","tense":"Past Simple"},{"origin":"У него был план","target":"He had a plan","tense":"Past Simple"},{"origin":"У них были проблемы","target":"They had problems","tense":"Past Simple"},{"origin":"У неё был брат","target":"She had a brother","tense":"Past Simple"},{"origin":"У меня было время подумать","target":"I had time to think","tense":"Past Simple"},{"origin":"У тебя было право знать","target":"You had the right to know","tense":"Past Simple"},{"origin":"У нас был хороший день","target":"We had a good day","tense":"Past Simple"},{"origin":"У него была возможность","target":"He had an opportunity","tense":"Past Simple"},{"origin":"У них был выбор","target":"They had a choice","tense":"Past Simple"},{"origin":"Я уже сделал это","target":"I have already done it","tense":"Present Perfect"},{"origin":"Мы уже видели этот фильм","target":"We have already seen this movie","tense":"Present Perfect"},{"origin":"Она уже ушла","target":"She has already left","tense":"Present Perfect"},{"origin":"Они уже приехали","target":"They have already arrived","tense":"Present Perfect"},{"origin":"Он уже закончил работу","target":"He has already finished the work","tense":"Present Perfect"},{"origin":"Я никогда не был там","target":"I have never been there","tense":"Present Perfect"},{"origin":"Ты когда-нибудь пробовал это?","target":"Have you ever tried this?","tense":"Present Perfect"},{"origin":"Мы ещё не решили","target":"We haven't decided yet","tense":"Present Perfect"},{"origin":"Она уже позавтракала","target":"She has already had breakfast","tense":"Present Perfect"},{"origin":"Они уже встречались раньше","target":"They have met before","tense":"Present Perfect"},{"origin":"У меня будет время завтра","target":"I will have time tomorrow","tense":"Future"},{"origin":"У нас будет вечеринка","target":"We will have a party","tense":"Future"},{"origin":"У неё будет ребёнок","target":"She will have a baby","tense":"Future"},{"origin":"У них будет шанс","target":"They will have a chance","tense":"Future"},{"origin":"У него будет собеседование","target":"He will have an interview","tense":"Future"},{"origin":"У тебя будет возможность","target":"You will have an opportunity","tense":"Future"},{"origin":"У меня будет встреча в три","target":"I will have a meeting at three","tense":"Future"},{"origin":"У нас будет много работы","target":"We will have a lot of work","tense":"Future"},{"origin":"У неё будет отпуск","target":"She will have a vacation","tense":"Future"},{"origin":"У них будет свадьба","target":"They will have a wedding","tense":"Future"},{"origin":"У меня была бы возможность","target":"I would have a chance","tense":"Conditional"},{"origin":"У нас было бы время","target":"We would have time","tense":"Conditional"},{"origin":"У неё был бы выбор","target":"She would have a choice","tense":"Conditional"},{"origin":"У них было бы решение","target":"They would have a solution","tense":"Conditional"},{"origin":"У него была бы идея","target":"He would have an idea","tense":"Conditional"},{"origin":"Я бы сделал это, если бы у меня было время","target":"I would have done it if I had had time","tense":"Conditional"},{"origin":"У тебя была бы возможность","target":"You would have an opportunity","tense":"Conditional"},{"origin":"У нас было бы больше денег","target":"We would have more money","tense":"Conditional"},{"origin":"У неё был бы шанс","target":"She would have a chance","tense":"Conditional"},{"origin":"У них было бы преимущество","target":"They would have an advantage","tense":"Conditional"},{"origin":"У меня есть головная боль","target":"I have a headache","tense":"Expression"},{"origin":"Повеселись!","target":"Have fun!","tense":"Expression"},{"origin":"Приятного аппетита!","target":"Have a nice meal!","tense":"Expression"},{"origin":"У меня есть право сказать","target":"I have the right to say","tense":"Expression"},{"origin":"Мне нужно поговорить с тобой","target":"I have to talk to you","tense":"Expression"},{"origin":"У неё простуда","target":"She has a cold","tense":"Expression"},{"origin":"Мне нужно идти","target":"I have to go","tense":"Expression"},{"origin":"У нас есть проблема","target":"We have a problem","tense":"Expression"},{"origin":"Хорошего дня!","target":"Have a nice day!","tense":"Expression"},{"origin":"У него есть талант","target":"He has talent","tense":"Expression"},{"origin":"У меня есть чувство, что...","target":"I have a feeling that...","tense":"Expression"},{"origin":"У тебя есть минутка?","target":"Do you have a minute?","tense":"Expression"},{"origin":"У неё есть опыт","target":"She has experience","tense":"Expression"},{"origin":"Мне нужно подумать об этом","target":"I have to think about it","tense":"Expression"},{"origin":"У них есть влияние","target":"They have influence","tense":"Expression"},{"origin":"У меня нет понятия","target":"I have no idea","tense":"Expression"},{"origin":"Хороших выходных!","target":"Have a good weekend!","tense":"Expression"},{"origin":"У неё есть точка зрения","target":"She has a point","tense":"Expression"},{"origin":"Мне нужно признать","target":"I have to admit","tense":"Expression"},{"origin":"У нас есть соглашение","target":"We have an agreement","tense":"Expression"},{"origin":"У меня три брата","target":"I have three brothers","tense":"Present"},{"origin":"У неё голубые глаза","target":"She has blue eyes","tense":"Present"},{"origin":"У нас большой сад","target":"We have a big garden","tense":"Present"},{"origin":"У него много друзей","target":"He has many friends","tense":"Present"},{"origin":"У них новая квартира","target":"They have a new apartment","tense":"Present"},{"origin":"У меня был плохой день","target":"I had a bad day","tense":"Past Simple"},{"origin":"У нас был долгий разговор","target":"We had a long conversation","tense":"Past Simple"},{"origin":"У неё была температура","target":"She had a fever","tense":"Past Simple"},{"origin":"У них был аргумент","target":"They had an argument","tense":"Past Simple"},{"origin":"У него была мечта","target":"He had a dream","tense":"Past Simple"},{"origin":"Я только что пообедал","target":"I have just had lunch","tense":"Present Perfect"},{"origin":"Мы уже обсудили это","target":"We have already discussed this","tense":"Present Perfect"},{"origin":"Она жила здесь пять лет","target":"She has lived here for five years","tense":"Present Perfect"},{"origin":"Они потеряли ключи","target":"They have lost their keys","tense":"Present Perfect"},{"origin":"Он изменил своё мнение","target":"He has changed his mind","tense":"Present Perfect"},{"origin":"У меня будет отпуск в июле","target":"I will have a vacation in July","tense":"Future"},{"origin":"У нас будет гость","target":"We will have a guest","tense":"Future"},{"origin":"У неё будет экзамен","target":"She will have an exam","tense":"Future"},{"origin":"У них будет проблема","target":"They will have a problem","tense":"Future"},{"origin":"У него будет успех","target":"He will have success","tense":"Future"},{"origin":"Если бы у меня были деньги","target":"If I had money","tense":"Conditional"},{"origin":"Я бы помог, если бы мог","target":"I would have helped if I could have","tense":"Conditional"},{"origin":"У неё было бы больше друзей","target":"She would have more friends","tense":"Conditional"},{"origin":"Мы бы выиграли, если бы попытались","target":"We would have won if we had tried","tense":"Conditional"},{"origin":"У них было бы меньше стресса","target":"They would have less stress","tense":"Conditional"}],"pt":[{"origin":"Eu tenho uma pergunta","target":"I have a question","tense":"Present"},{"origin":"Ela tem um cachorro","target":"She has a dog","tense":"Present"},{"origin":"Eles têm tempo","target":"They have time","tense":"Present"},{"origin":"Nós temos uma casa","target":"We have a house","tense":"Present"},{"origin":"Ele tem um carro","target":"He has a car","tense":"Present"},{"origin":"Eu tenho uma ideia","target":"I have an idea","tense":"Present"},{"origin":"Você tem dinheiro?","target":"Do you have money?","tense":"Present"},{"origin":"Nós não temos escolha","target":"We don't have a choice","tense":"Present"},{"origin":"Ela tem um emprego","target":"She has a job","tense":"Present"},{"origin":"Eles têm filhos","target":"They have children","tense":"Present"},{"origin":"Eu tive uma oportunidade","target":"I had a chance","tense":"Past Simple"},{"origin":"Nós tivemos uma reunião","target":"We had a meeting","tense":"Past Simple"},{"origin":"Ele teve um plano","target":"He had a plan","tense":"Past Simple"},{"origin":"Eles tiveram problemas","target":"They had problems","tense":"Past Simple"},{"origin":"Ela teve um irmão","target":"She had a brother","tense":"Past Simple"},{"origin":"Eu tive tempo para pensar","target":"I had time to think","tense":"Past Simple"},{"origin":"Você tinha o direito de saber","target":"You had the right to know","tense":"Past Simple"},{"origin":"Nós tivemos um bom dia","target":"We had a good day","tense":"Past Simple"},{"origin":"Ele teve uma oportunidade","target":"He had an opportunity","tense":"Past Simple"},{"origin":"Eles tiveram uma escolha","target":"They had a choice","tense":"Past Simple"},{"origin":"Eu já fiz isso","target":"I have already done it","tense":"Present Perfect"},{"origin":"Nós já vimos este filme","target":"We have already seen this movie","tense":"Present Perfect"},{"origin":"Ela já saiu","target":"She has already left","tense":"Present Perfect"},{"origin":"Eles já chegaram","target":"They have already arrived","tense":"Present Perfect"},{"origin":"Ele já terminou o trabalho","target":"He has already finished the work","tense":"Present Perfect"},{"origin":"Eu nunca estive lá","target":"I have never been there","tense":"Present Perfect"},{"origin":"Você já experimentou isso?","target":"Have you ever tried this?","tense":"Present Perfect"},{"origin":"Nós ainda não decidimos","target":"We haven't decided yet","tense":"Present Perfect"},{"origin":"Ela já tomou café da manhã","target":"She has already had breakfast","tense":"Present Perfect"},{"origin":"Eles já se conheceram antes","target":"They have met before","tense":"Present Perfect"},{"origin":"Eu terei tempo amanhã","target":"I will have time tomorrow","tense":"Future"},{"origin":"Nós teremos uma festa","target":"We will have a party","tense":"Future"},{"origin":"Ela terá um bebê","target":"She will have a baby","tense":"Future"},{"origin":"Eles terão uma chance","target":"They will have a chance","tense":"Future"},{"origin":"Ele terá uma entrevista","target":"He will have an interview","tense":"Future"},{"origin":"Você terá uma oportunidade","target":"You will have an opportunity","tense":"Future"},{"origin":"Eu terei uma reunião às três","target":"I will have a meeting at three","tense":"Future"},{"origin":"Nós teremos muito trabalho","target":"We will have a lot of work","tense":"Future"},{"origin":"Ela terá férias","target":"She will have a vacation","tense":"Future"},{"origin":"Eles terão um casamento","target":"They will have a wedding","tense":"Future"},{"origin":"Eu teria uma chance","target":"I would have a chance","tense":"Conditional"},{"origin":"Nós teríamos tempo","target":"We would have time","tense":"Conditional"},{"origin":"Ela teria uma escolha","target":"She would have a choice","tense":"Conditional"},{"origin":"Eles teriam uma solução","target":"They would have a solution","tense":"Conditional"},{"origin":"Ele teria uma ideia","target":"He would have an idea","tense":"Conditional"},{"origin":"Eu teria feito se tivesse tempo","target":"I would have done it if I had had time","tense":"Conditional"},{"origin":"Você teria uma oportunidade","target":"You would have an opportunity","tense":"Conditional"},{"origin":"Nós teríamos mais dinheiro","target":"We would have more money","tense":"Conditional"},{"origin":"Ela teria uma chance","target":"She would have a chance","tense":"Conditional"},{"origin":"Eles teriam uma vantagem","target":"They would have an advantage","tense":"Conditional"},{"origin":"Eu tenho dor de cabeça","target":"I have a headache","tense":"Expression"},{"origin":"Divirta-se!","target":"Have fun!","tense":"Expression"},{"origin":"Bom apetite!","target":"Have a nice meal!","tense":"Expression"},{"origin":"Eu tenho o direito de dizer","target":"I have the right to say","tense":"Expression"},{"origin":"Eu tenho que falar com você","target":"I have to talk to you","tense":"Expression"},{"origin":"Ela está resfriada","target":"She has a cold","tense":"Expression"},{"origin":"Eu tenho que ir","target":"I have to go","tense":"Expression"},{"origin":"Nós temos um problema","target":"We have a problem","tense":"Expression"},{"origin":"Tenha um bom dia!","target":"Have a nice day!","tense":"Expression"},{"origin":"Ele tem talento","target":"He has talent","tense":"Expression"},{"origin":"Eu tenho a sensação de que...","target":"I have a feeling that...","tense":"Expression"},{"origin":"Você tem um minuto?","target":"Do you have a minute?","tense":"Expression"},{"origin":"Ela tem experiência","target":"She has experience","tense":"Expression"},{"origin":"Eu tenho que pensar sobre isso","target":"I have to think about it","tense":"Expression"},{"origin":"Eles têm influência","target":"They have influence","tense":"Expression"},{"origin":"Eu não tenho ideia","target":"I have no idea","tense":"Expression"},{"origin":"Tenha um bom fim de semana!","target":"Have a good weekend!","tense":"Expression"},{"origin":"Ela tem razão","target":"She has a point","tense":"Expression"},{"origin":"Eu tenho que admitir","target":"I have to admit","tense":"Expression"},{"origin":"Nós temos um acordo","target":"We have an agreement","tense":"Expression"},{"origin":"Eu tenho três irmãos","target":"I have three brothers","tense":"Present"},{"origin":"Ela tem olhos azuis","target":"She has blue eyes","tense":"Present"},{"origin":"Nós temos um jardim grande","target":"We have a big garden","tense":"Present"},{"origin":"Ele tem muitos amigos","target":"He has many friends","tense":"Present"},{"origin":"Eles têm um apartamento novo","target":"They have a new apartment","tense":"Present"},{"origin":"Eu tive um dia ruim","target":"I had a bad day","tense":"Past Simple"},{"origin":"Nós tivemos uma conversa longa","target":"We had a long conversation","tense":"Past Simple"},{"origin":"Ela teve febre","target":"She had a fever","tense":"Past Simple"},{"origin":"Eles tiveram uma discussão","target":"They had an argument","tense":"Past Simple"},{"origin":"Ele teve um sonho","target":"He had a dream","tense":"Past Simple"},{"origin":"Eu acabei de almoçar","target":"I have just had lunch","tense":"Present Perfect"},{"origin":"Nós já discutimos isso","target":"We have already discussed this","tense":"Present Perfect"},{"origin":"Ela mora aqui há cinco anos","target":"She has lived here for five years","tense":"Present Perfect"},{"origin":"Eles perderam as chaves","target":"They have lost their keys","tense":"Present Perfect"},{"origin":"Ele mudou de ideia","target":"He has changed his mind","tense":"Present Perfect"},{"origin":"Eu terei férias em julho","target":"I will have a vacation in July","tense":"Future"},{"origin":"Nós teremos um convidado","target":"We will have a guest","tense":"Future"},{"origin":"Ela terá um exame","target":"She will have an exam","tense":"Future"},{"origin":"Eles terão um problema","target":"They will have a problem","tense":"Future"},{"origin":"Ele terá sucesso","target":"He will have success","tense":"Future"},{"origin":"Se eu tivesse dinheiro","target":"If I had money","tense":"Conditional"},{"origin":"Eu teria ajudado se pudesse","target":"I would have helped if I could have","tense":"Conditional"},{"origin":"Ela teria mais amigos","target":"She would have more friends","tense":"Conditional"},{"origin":"Nós teríamos ganho se tentássemos","target":"We would have won if we had tried","tense":"Conditional"},{"origin":"Eles teriam menos estresse","target":"They would have less stress","tense":"Conditional"}],"de":[{"origin":"Ich habe eine Frage","target":"I have a question","tense":"Present"},{"origin":"Sie hat einen Hund","target":"She has a dog","tense":"Present"},{"origin":"Sie haben Zeit","target":"They have time","tense":"Present"},{"origin":"Wir haben ein Haus","target":"We have a house","tense":"Present"},{"origin":"Er hat ein Auto","target":"He has a car","tense":"Present"},{"origin":"Ich habe eine Idee","target":"I have an idea","tense":"Present"},{"origin":"Hast du Geld?","target":"Do you have money?","tense":"Present"},{"origin":"Wir haben keine Wahl","target":"We don't have a choice","tense":"Present"},{"origin":"Sie hat einen Job","target":"She has a job","tense":"Present"},{"origin":"Sie haben Kinder","target":"They have children","tense":"Present"},{"origin":"Ich hatte eine Chance","target":"I had a chance","tense":"Past Simple"},{"origin":"Wir hatten ein Meeting","target":"We had a meeting","tense":"Past Simple"},{"origin":"Er hatte einen Plan","target":"He had a plan","tense":"Past Simple"},{"origin":"Sie hatten Probleme","target":"They had problems","tense":"Past Simple"},{"origin":"Sie hatte einen Bruder","target":"She had a brother","tense":"Past Simple"},{"origin":"Ich hatte Zeit zum Nachdenken","target":"I had time to think","tense":"Past Simple"},{"origin":"Du hattest das Recht zu wissen","target":"You had the right to know","tense":"Past Simple"},{"origin":"Wir hatten einen guten Tag","target":"We had a good day","tense":"Past Simple"},{"origin":"Er hatte eine Gelegenheit","target":"He had an opportunity","tense":"Past Simple"},{"origin":"Sie hatten eine Wahl","target":"They had a choice","tense":"Past Simple"},{"origin":"Ich habe es schon gemacht","target":"I have already done it","tense":"Present Perfect"},{"origin":"Wir haben diesen Film schon gesehen","target":"We have already seen this movie","tense":"Present Perfect"},{"origin":"Sie ist schon gegangen","target":"She has already left","tense":"Present Perfect"},{"origin":"Sie sind schon angekommen","target":"They have already arrived","tense":"Present Perfect"},{"origin":"Er hat die Arbeit schon beendet","target":"He has already finished the work","tense":"Present Perfect"},{"origin":"Ich bin nie dort gewesen","target":"I have never been there","tense":"Present Perfect"},{"origin":"Hast du das jemals probiert?","target":"Have you ever tried this?","tense":"Present Perfect"},{"origin":"Wir haben noch nicht entschieden","target":"We haven't decided yet","tense":"Present Perfect"},{"origin":"Sie hat schon gefrühstückt","target":"She has already had breakfast","tense":"Present Perfect"},{"origin":"Sie haben sich schon getroffen","target":"They have met before","tense":"Present Perfect"},{"origin":"Ich werde morgen Zeit haben","target":"I will have time tomorrow","tense":"Future"},{"origin":"Wir werden eine Party haben","target":"We will have a party","tense":"Future"},{"origin":"Sie wird ein Baby haben","target":"She will have a baby","tense":"Future"},{"origin":"Sie werden eine Chance haben","target":"They will have a chance","tense":"Future"},{"origin":"Er wird ein Interview haben","target":"He will have an interview","tense":"Future"},{"origin":"Du wirst eine Gelegenheit haben","target":"You will have an opportunity","tense":"Future"},{"origin":"Ich werde um drei ein Meeting haben","target":"I will have a meeting at three","tense":"Future"},{"origin":"Wir werden viel Arbeit haben","target":"We will have a lot of work","tense":"Future"},{"origin":"Sie wird Urlaub haben","target":"She will have a vacation","tense":"Future"},{"origin":"Sie werden eine Hochzeit haben","target":"They will have a wedding","tense":"Future"},{"origin":"Ich hätte eine Chance","target":"I would have a chance","tense":"Conditional"},{"origin":"Wir hätten Zeit","target":"We would have time","tense":"Conditional"},{"origin":"Sie hätte eine Wahl","target":"She would have a choice","tense":"Conditional"},{"origin":"Sie hätten eine Lösung","target":"They would have a solution","tense":"Conditional"},{"origin":"Er hätte eine Idee","target":"He would have an idea","tense":"Conditional"},{"origin":"Ich hätte es gemacht, wenn ich Zeit gehabt hätte","target":"I would have done it if I had had time","tense":"Conditional"},{"origin":"Du hättest eine Gelegenheit","target":"You would have an opportunity","tense":"Conditional"},{"origin":"Wir hätten mehr Geld","target":"We would have more money","tense":"Conditional"},{"origin":"Sie hätte eine Chance","target":"She would have a chance","tense":"Conditional"},{"origin":"Sie hätten einen Vorteil","target":"They would have an advantage","tense":"Conditional"},{"origin":"Ich habe Kopfschmerzen","target":"I have a headache","tense":"Expression"},{"origin":"Viel Spaß!","target":"Have fun!","tense":"Expression"},{"origin":"Guten Appetit!","target":"Have a nice meal!","tense":"Expression"},{"origin":"Ich habe das Recht zu sagen","target":"I have the right to say","tense":"Expression"},{"origin":"Ich muss mit dir reden","target":"I have to talk to you","tense":"Expression"},{"origin":"Sie hat eine Erkältung","target":"She has a cold","tense":"Expression"},{"origin":"Ich muss gehen","target":"I have to go","tense":"Expression"},{"origin":"Wir haben ein Problem","target":"We have a problem","tense":"Expression"},{"origin":"Hab einen schönen Tag!","target":"Have a nice day!","tense":"Expression"},{"origin":"Er hat Talent","target":"He has talent","tense":"Expression"},{"origin":"Ich habe das Gefühl, dass...","target":"I have a feeling that...","tense":"Expression"},{"origin":"Hast du eine Minute?","target":"Do you have a minute?","tense":"Expression"},{"origin":"Sie hat Erfahrung","target":"She has experience","tense":"Expression"},{"origin":"Ich muss darüber nachdenken","target":"I have to think about it","tense":"Expression"},{"origin":"Sie haben Einfluss","target":"They have influence","tense":"Expression"},{"origin":"Ich habe keine Ahnung","target":"I have no idea","tense":"Expression"},{"origin":"Hab ein schönes Wochenende!","target":"Have a good weekend!","tense":"Expression"},{"origin":"Sie hat recht","target":"She has a point","tense":"Expression"},{"origin":"Ich muss zugeben","target":"I have to admit","tense":"Expression"},{"origin":"Wir haben eine Vereinbarung","target":"We have an agreement","tense":"Expression"},{"origin":"Ich habe drei Brüder","target":"I have three brothers","tense":"Present"},{"origin":"Sie hat blaue Augen","target":"She has blue eyes","tense":"Present"},{"origin":"Wir haben einen großen Garten","target":"We have a big garden","tense":"Present"},{"origin":"Er hat viele Freunde","target":"He has many friends","tense":"Present"},{"origin":"Sie haben eine neue Wohnung","target":"They have a new apartment","tense":"Present"},{"origin":"Ich hatte einen schlechten Tag","target":"I had a bad day","tense":"Past Simple"},{"origin":"Wir hatten ein langes Gespräch","target":"We had a long conversation","tense":"Past Simple"},{"origin":"Sie hatte Fieber","target":"She had a fever","tense":"Past Simple"},{"origin":"Sie hatten einen Streit","target":"They had an argument","tense":"Past Simple"},{"origin":"Er hatte einen Traum","target":"He had a dream","tense":"Past Simple"},{"origin":"Ich habe gerade zu Mittag gegessen","target":"I have just had lunch","tense":"Present Perfect"},{"origin":"Wir haben das schon besprochen","target":"We have already discussed this","tense":"Present Perfect"},{"origin":"Sie wohnt seit fünf Jahren hier","target":"She has lived here for five years","tense":"Present Perfect"},{"origin":"Sie haben ihre Schlüssel verloren","target":"They have lost their keys","tense":"Present Perfect"},{"origin":"Er hat seine Meinung geändert","target":"He has changed his mind","tense":"Present Perfect"},{"origin":"Ich werde im Juli Urlaub haben","target":"I will have a vacation in July","tense":"Future"},{"origin":"Wir werden einen Gast haben","target":"We will have a guest","tense":"Future"},{"origin":"Sie wird eine Prüfung haben","target":"She will have an exam","tense":"Future"},{"origin":"Sie werden ein Problem haben","target":"They will have a problem","tense":"Future"},{"origin":"Er wird Erfolg haben","target":"He will have success","tense":"Future"},{"origin":"Wenn ich Geld hätte","target":"If I had money","tense":"Conditional"},{"origin":"Ich hätte geholfen, wenn ich gekonnt hätte","target":"I would have helped if I could have","tense":"Conditional"},{"origin":"Sie hätte mehr Freunde","target":"She would have more friends","tense":"Conditional"},{"origin":"Wir hätten gewonnen, wenn wir es versucht hätten","target":"We would have won if we had tried","tense":"Conditional"},{"origin":"Sie hätten weniger Stress","target":"They would have less stress","tense":"Conditional"}],"fr":[{"origin":"J'ai une question","target":"I have a question","tense":"Present"},{"origin":"Elle a un chien","target":"She has a dog","tense":"Present"},{"origin":"Ils ont du temps","target":"They have time","tense":"Present"},{"origin":"Nous avons une maison","target":"We have a house","tense":"Present"},{"origin":"Il a une voiture","target":"He has a car","tense":"Present"},{"origin":"J'ai une idée","target":"I have an idea","tense":"Present"},{"origin":"Tu as de l'argent?","target":"Do you have money?","tense":"Present"},{"origin":"Nous n'avons pas le choix","target":"We don't have a choice","tense":"Present"},{"origin":"Elle a un travail","target":"She has a job","tense":"Present"},{"origin":"Ils ont des enfants","target":"They have children","tense":"Present"},{"origin":"J'ai eu une chance","target":"I had a chance","tense":"Past Simple"},{"origin":"Nous avons eu une réunion","target":"We had a meeting","tense":"Past Simple"},{"origin":"Il avait un plan","target":"He had a plan","tense":"Past Simple"},{"origin":"Ils ont eu des problèmes","target":"They had problems","tense":"Past Simple"},{"origin":"Elle avait un frère","target":"She had a brother","tense":"Past Simple"},{"origin":"J'ai eu le temps de réfléchir","target":"I had time to think","tense":"Past Simple"},{"origin":"Tu avais le droit de savoir","target":"You had the right to know","tense":"Past Simple"},{"origin":"Nous avons eu une bonne journée","target":"We had a good day","tense":"Past Simple"},{"origin":"Il a eu une opportunité","target":"He had an opportunity","tense":"Past Simple"},{"origin":"Ils avaient un choix","target":"They had a choice","tense":"Past Simple"},{"origin":"J'ai déjà fait ça","target":"I have already done it","tense":"Present Perfect"},{"origin":"Nous avons déjà vu ce film","target":"We have already seen this movie","tense":"Present Perfect"},{"origin":"Elle est déjà partie","target":"She has already left","tense":"Present Perfect"},{"origin":"Ils sont déjà arrivés","target":"They have already arrived","tense":"Present Perfect"},{"origin":"Il a déjà fini le travail","target":"He has already finished the work","tense":"Present Perfect"},{"origin":"Je ne suis jamais allé là-bas","target":"I have never been there","tense":"Present Perfect"},{"origin":"As-tu déjà essayé ça?","target":"Have you ever tried this?","tense":"Present Perfect"},{"origin":"Nous n'avons pas encore décidé","target":"We haven't decided yet","tense":"Present Perfect"},{"origin":"Elle a déjà pris le petit-déjeuner","target":"She has already had breakfast","tense":"Present Perfect"},{"origin":"Ils se sont déjà rencontrés","target":"They have met before","tense":"Present Perfect"},{"origin":"J'aurai du temps demain","target":"I will have time tomorrow","tense":"Future"},{"origin":"Nous aurons une fête","target":"We will have a party","tense":"Future"},{"origin":"Elle aura un bébé","target":"She will have a baby","tense":"Future"},{"origin":"Ils auront une chance","target":"They will have a chance","tense":"Future"},{"origin":"Il aura un entretien","target":"He will have an interview","tense":"Future"},{"origin":"Tu auras une opportunité","target":"You will have an opportunity","tense":"Future"},{"origin":"J'aurai une réunion à trois heures","target":"I will have a meeting at three","tense":"Future"},{"origin":"Nous aurons beaucoup de travail","target":"We will have a lot of work","tense":"Future"},{"origin":"Elle aura des vacances","target":"She will have a vacation","tense":"Future"},{"origin":"Ils auront un mariage","target":"They will have a wedding","tense":"Future"},{"origin":"J'aurais une chance","target":"I would have a chance","tense":"Conditional"},{"origin":"Nous aurions du temps","target":"We would have time","tense":"Conditional"},{"origin":"Elle aurait un choix","target":"She would have a choice","tense":"Conditional"},{"origin":"Ils auraient une solution","target":"They would have a solution","tense":"Conditional"},{"origin":"Il aurait une idée","target":"He would have an idea","tense":"Conditional"},{"origin":"J'aurais fait ça si j'avais eu le temps","target":"I would have done it if I had had time","tense":"Conditional"},{"origin":"Tu aurais une opportunité","target":"You would have an opportunity","tense":"Conditional"},{"origin":"Nous aurions plus d'argent","target":"We would have more money","tense":"Conditional"},{"origin":"Elle aurait une chance","target":"She would have a chance","tense":"Conditional"},{"origin":"Ils auraient un avantage","target":"They would have an advantage","tense":"Conditional"},{"origin":"J'ai mal à la tête","target":"I have a headache","tense":"Expression"},{"origin":"Amuse-toi bien!","target":"Have fun!","tense":"Expression"},{"origin":"Bon appétit!","target":"Have a nice meal!","tense":"Expression"},{"origin":"J'ai le droit de dire","target":"I have the right to say","tense":"Expression"},{"origin":"Je dois te parler","target":"I have to talk to you","tense":"Expression"},{"origin":"Elle a un rhume","target":"She has a cold","tense":"Expression"},{"origin":"Je dois y aller","target":"I have to go","tense":"Expression"},{"origin":"Nous avons un problème","target":"We have a problem","tense":"Expression"},{"origin":"Passe une bonne journée!","target":"Have a nice day!","tense":"Expression"},{"origin":"Il a du talent","target":"He has talent","tense":"Expression"},{"origin":"J'ai le sentiment que...","target":"I have a feeling that...","tense":"Expression"},{"origin":"Tu as une minute?","target":"Do you have a minute?","tense":"Expression"},{"origin":"Elle a de l'expérience","target":"She has experience","tense":"Expression"},{"origin":"Je dois y réfléchir","target":"I have to think about it","tense":"Expression"},{"origin":"Ils ont de l'influence","target":"They have influence","tense":"Expression"},{"origin":"Je n'ai aucune idée","target":"I have no idea","tense":"Expression"},{"origin":"Passe un bon week-end!","target":"Have a good weekend!","tense":"Expression"},{"origin":"Elle a raison","target":"She has a point","tense":"Expression"},{"origin":"Je dois admettre","target":"I have to admit","tense":"Expression"},{"origin":"Nous avons un accord","target":"We have an agreement","tense":"Expression"},{"origin":"J'ai trois frères","target":"I have three brothers","tense":"Present"},{"origin":"Elle a les yeux bleus","target":"She has blue eyes","tense":"Present"},{"origin":"Nous avons un grand jardin","target":"We have a big garden","tense":"Present"},{"origin":"Il a beaucoup d'amis","target":"He has many friends","tense":"Present"},{"origin":"Ils ont un nouvel appartement","target":"They have a new apartment","tense":"Present"},{"origin":"J'ai eu une mauvaise journée","target":"I had a bad day","tense":"Past Simple"},{"origin":"Nous avons eu une longue conversation","target":"We had a long conversation","tense":"Past Simple"},{"origin":"Elle avait de la fièvre","target":"She had a fever","tense":"Past Simple"},{"origin":"Ils ont eu une dispute","target":"They had an argument","tense":"Past Simple"},{"origin":"Il a fait un rêve","target":"He had a dream","tense":"Past Simple"},{"origin":"Je viens de déjeuner","target":"I have just had lunch","tense":"Present Perfect"},{"origin":"Nous avons déjà discuté de ça","target":"We have already discussed this","tense":"Present Perfect"},{"origin":"Elle habite ici depuis cinq ans","target":"She has lived here for five years","tense":"Present Perfect"},{"origin":"Ils ont perdu leurs clés","target":"They have lost their keys","tense":"Present Perfect"},{"origin":"Il a changé d'avis","target":"He has changed his mind","tense":"Present Perfect"},{"origin":"J'aurai des vacances en juillet","target":"I will have a vacation in July","tense":"Future"},{"origin":"Nous aurons un invité","target":"We will have a guest","tense":"Future"},{"origin":"Elle aura un examen","target":"She will have an exam","tense":"Future"},{"origin":"Ils auront un problème","target":"They will have a problem","tense":"Future"},{"origin":"Il aura du succès","target":"He will have success","tense":"Future"},{"origin":"Si j'avais de l'argent","target":"If I had money","tense":"Conditional"},{"origin":"J'aurais aidé si j'avais pu","target":"I would have helped if I could have","tense":"Conditional"},{"origin":"Elle aurait plus d'amis","target":"She would have more friends","tense":"Conditional"},{"origin":"Nous aurions gagné si nous avions essayé","target":"We would have won if we had tried","tense":"Conditional"},{"origin":"Ils auraient moins de stress","target":"They would have less stress","tense":"Conditional"}]}}