{"slug":"use","name":"🇬🇧 Verb USE","meaning":"to employ, to utilize","verb_forms":["use","uses","used","using"],"phrases":{"ru":[{"origin":"Я использую компьютер","target":"I use a computer","tense":"Present"},{"origin":"Ты используешь мой телефон","target":"You use my phone","tense":"Present"},{"origin":"Он использует Интернет","target":"He uses the Internet","tense":"Present"},{"origin":"Она использует этот метод","target":"She uses this method","tense":"Present"},{"origin":"Мы используем эту программу","target":"We use this program","tense":"Present"},{"origin":"Они используют общественный транспорт","target":"They use public transport","tense":"Present"},{"origin":"Я использовал твою ручку","target":"I used your pen","tense":"Past Simple"},{"origin":"Ты использовал мою идею","target":"You used my idea","tense":"Past Simple"},{"origin":"Он использовал неправильный инструмент","target":"He used the wrong tool","tense":"Past Simple"},{"origin":"Она использовала кредитную карту","target":"She used a credit card","tense":"Past Simple"},{"origin":"Мы использовали старую технику","target":"We used old equipment","tense":"Past Simple"},{"origin":"Они использовали все ресурсы","target":"They used all the resources","tense":"Past Simple"},{"origin":"Я использую сейчас туалет","target":"I am using the bathroom now","tense":"Present Continuous"},{"origin":"Ты используешь мою машину?","target":"Are you using my car?","tense":"Present Continuous"},{"origin":"Он использует новую стратегию","target":"He is using a new strategy","tense":"Present Continuous"},{"origin":"Она использует мой компьютер","target":"She is using my computer","tense":"Present Continuous"},{"origin":"Мы используем новую систему","target":"We are using a new system","tense":"Present Continuous"},{"origin":"Они используют наши данные","target":"They are using our data","tense":"Present Continuous"},{"origin":"Я использовал принтер, когда он сломался","target":"I was using the printer when it broke","tense":"Past Continuous"},{"origin":"Ты использовал мой ноутбук?","target":"Were you using my laptop?","tense":"Past Continuous"},{"origin":"Он использовал телефон весь день","target":"He was using the phone all day","tense":"Past Continuous"},{"origin":"Она использовала эту комнату","target":"She was using this room","tense":"Past Continuous"},{"origin":"Мы использовали старую версию","target":"We were using the old version","tense":"Past Continuous"},{"origin":"Они использовали наше оборудование","target":"They were using our equipment","tense":"Past Continuous"},{"origin":"Я никогда не использовал это","target":"I have never used this","tense":"Present Perfect"},{"origin":"Ты уже использовал новое приложение?","target":"Have you used the new app yet?","tense":"Present Perfect"},{"origin":"Он использовал этот трюк раньше","target":"He has used this trick before","tense":"Present Perfect"},{"origin":"Она уже использовала все попытки","target":"She has already used all attempts","tense":"Present Perfect"},{"origin":"Мы использовали этот подход много раз","target":"We have used this approach many times","tense":"Present Perfect"},{"origin":"Они использовали весь бюджет","target":"They have used the entire budget","tense":"Present Perfect"},{"origin":"Я буду использовать другой метод","target":"I will use a different method","tense":"Future"},{"origin":"Ты будешь использовать мою машину?","target":"Will you use my car?","tense":"Future"},{"origin":"Он будет использовать эту информацию","target":"He will use this information","tense":"Future"},{"origin":"Она будет использовать новую технологию","target":"She will use new technology","tense":"Future"},{"origin":"Мы будем использовать лучшие материалы","target":"We will use the best materials","tense":"Future"},{"origin":"Они будут использовать наш план","target":"They will use our plan","tense":"Future"},{"origin":"Я бы использовал другой подход","target":"I would use a different approach","tense":"Conditional"},{"origin":"Ты бы использовал это?","target":"Would you use this?","tense":"Conditional"},{"origin":"Он бы использовал больше времени","target":"He would use more time","tense":"Conditional"},{"origin":"Она бы использовала помощь","target":"She would use some help","tense":"Conditional"},{"origin":"Мы бы использовали твой совет","target":"We would use your advice","tense":"Conditional"},{"origin":"Они бы использовали другой способ","target":"They would use another way","tense":"Conditional"},{"origin":"Используй свой мозг","target":"Use your brain","tense":"Imperative"},{"origin":"Используй эту возможность","target":"Use this opportunity","tense":"Imperative"},{"origin":"Используйте эту дверь","target":"Use this door","tense":"Imperative"},{"origin":"Используйте инструкции","target":"Use the instructions","tense":"Imperative"},{"origin":"Не используй это","target":"Don't use this","tense":"Imperative"},{"origin":"Не используйте лифт","target":"Don't use the elevator","tense":"Imperative"},{"origin":"Я раньше жил в Москве","target":"I used to live in Moscow","tense":"Expressions"},{"origin":"Ты раньше играл в футбол?","target":"Did you use to play football?","tense":"Expressions"},{"origin":"Он раньше курил","target":"He used to smoke","tense":"Expressions"},{"origin":"Она раньше работала здесь","target":"She used to work here","tense":"Expressions"},{"origin":"Мы раньше встречались каждый день","target":"We used to meet every day","tense":"Expressions"},{"origin":"Они раньше были друзьями","target":"They used to be friends","tense":"Expressions"},{"origin":"Я не использую социальные сети","target":"I don't use social media","tense":"Present"},{"origin":"Ты не используешь правильный подход","target":"You don't use the right approach","tense":"Present"},{"origin":"Он не использует насилие","target":"He doesn't use violence","tense":"Present"},{"origin":"Она не использует макияж","target":"She doesn't use makeup","tense":"Present"},{"origin":"Мы не используем пластик","target":"We don't use plastic","tense":"Present"},{"origin":"Они не используют химикаты","target":"They don't use chemicals","tense":"Present"},{"origin":"Я не использовал силу","target":"I didn't use force","tense":"Past Simple"},{"origin":"Ты не использовал шанс","target":"You didn't use the chance","tense":"Past Simple"},{"origin":"Он не использовал моё имя","target":"He didn't use my name","tense":"Past Simple"},{"origin":"Она не использовала инструкцию","target":"She didn't use the manual","tense":"Past Simple"},{"origin":"Мы не использовали правильные слова","target":"We didn't use the right words","tense":"Past Simple"},{"origin":"Они не использовали оружие","target":"They didn't use weapons","tense":"Past Simple"},{"origin":"Что ты используешь для этого?","target":"What do you use for this?","tense":"Present"},{"origin":"Как ты используешь это?","target":"How do you use this?","tense":"Present"},{"origin":"Почему он использует это?","target":"Why does he use this?","tense":"Present"},{"origin":"Когда ты использовал это?","target":"When did you use this?","tense":"Past Simple"},{"origin":"Где они используют это?","target":"Where do they use this?","tense":"Present"},{"origin":"Кто использует мой компьютер?","target":"Who is using my computer?","tense":"Present Continuous"},{"origin":"Я привык к холоду","target":"I am used to the cold","tense":"Expressions"},{"origin":"Ты привык к шуму","target":"You are used to the noise","tense":"Expressions"},{"origin":"Он привык вставать рано","target":"He is used to getting up early","tense":"Expressions"},{"origin":"Она привыкла работать одна","target":"She is used to working alone","tense":"Expressions"},{"origin":"Мы привыкли к жаре","target":"We are used to the heat","tense":"Expressions"},{"origin":"Они привыкли к давлению","target":"They are used to pressure","tense":"Expressions"},{"origin":"Я привыкаю к новой работе","target":"I am getting used to the new job","tense":"Expressions"},{"origin":"Ты привыкаешь к новому дому","target":"You are getting used to the new house","tense":"Expressions"},{"origin":"Он привыкает к новой школе","target":"He is getting used to the new school","tense":"Expressions"},{"origin":"Она привыкает к новой стране","target":"She is getting used to the new country","tense":"Expressions"}],"pt":[{"origin":"Eu uso um computador","target":"I use a computer","tense":"Present"},{"origin":"Tu usas o meu telefone","target":"You use my phone","tense":"Present"},{"origin":"Ele usa a Internet","target":"He uses the Internet","tense":"Present"},{"origin":"Ela usa este método","target":"She uses this method","tense":"Present"},{"origin":"Nós usamos este programa","target":"We use this program","tense":"Present"},{"origin":"Eles usam transportes públicos","target":"They use public transport","tense":"Present"},{"origin":"Eu usei a tua caneta","target":"I used your pen","tense":"Past Simple"},{"origin":"Tu usaste a minha ideia","target":"You used my idea","tense":"Past Simple"},{"origin":"Ele usou a ferramenta errada","target":"He used the wrong tool","tense":"Past Simple"},{"origin":"Ela usou um cartão de crédito","target":"She used a credit card","tense":"Past Simple"},{"origin":"Nós usámos equipamento antigo","target":"We used old equipment","tense":"Past Simple"},{"origin":"Eles usaram todos os recursos","target":"They used all the resources","tense":"Past Simple"},{"origin":"Eu estou a usar a casa de banho agora","target":"I am using the bathroom now","tense":"Present Continuous"},{"origin":"Tu estás a usar o meu carro?","target":"Are you using my car?","tense":"Present Continuous"},{"origin":"Ele está a usar uma nova estratégia","target":"He is using a new strategy","tense":"Present Continuous"},{"origin":"Ela está a usar o meu computador","target":"She is using my computer","tense":"Present Continuous"},{"origin":"Nós estamos a usar um sistema novo","target":"We are using a new system","tense":"Present Continuous"},{"origin":"Eles estão a usar os nossos dados","target":"They are using our data","tense":"Present Continuous"},{"origin":"Eu estava a usar a impressora quando avariou","target":"I was using the printer when it broke","tense":"Past Continuous"},{"origin":"Tu estavas a usar o meu portátil?","target":"Were you using my laptop?","tense":"Past Continuous"},{"origin":"Ele estava a usar o telefone o dia todo","target":"He was using the phone all day","tense":"Past Continuous"},{"origin":"Ela estava a usar esta sala","target":"She was using this room","tense":"Past Continuous"},{"origin":"Nós estávamos a usar a versão antiga","target":"We were using the old version","tense":"Past Continuous"},{"origin":"Eles estavam a usar o nosso equipamento","target":"They were using our equipment","tense":"Past Continuous"},{"origin":"Eu nunca usei isto","target":"I have never used this","tense":"Present Perfect"},{"origin":"Tu já usaste a nova aplicação?","target":"Have you used the new app yet?","tense":"Present Perfect"},{"origin":"Ele usou este truque antes","target":"He has used this trick before","tense":"Present Perfect"},{"origin":"Ela já usou todas as tentativas","target":"She has already used all attempts","tense":"Present Perfect"},{"origin":"Nós usámos esta abordagem muitas vezes","target":"We have used this approach many times","tense":"Present Perfect"},{"origin":"Eles usaram todo o orçamento","target":"They have used the entire budget","tense":"Present Perfect"},{"origin":"Eu vou usar um método diferente","target":"I will use a different method","tense":"Future"},{"origin":"Tu vais usar o meu carro?","target":"Will you use my car?","tense":"Future"},{"origin":"Ele vai usar esta informação","target":"He will use this information","tense":"Future"},{"origin":"Ela vai usar nova tecnologia","target":"She will use new technology","tense":"Future"},{"origin":"Nós vamos usar os melhores materiais","target":"We will use the best materials","tense":"Future"},{"origin":"Eles vão usar o nosso plano","target":"They will use our plan","tense":"Future"},{"origin":"Eu usaria uma abordagem diferente","target":"I would use a different approach","tense":"Conditional"},{"origin":"Tu usarias isto?","target":"Would you use this?","tense":"Conditional"},{"origin":"Ele usaria mais tempo","target":"He would use more time","tense":"Conditional"},{"origin":"Ela usaria alguma ajuda","target":"She would use some help","tense":"Conditional"},{"origin":"Nós usaríamos o teu conselho","target":"We would use your advice","tense":"Conditional"},{"origin":"Eles usariam outra maneira","target":"They would use another way","tense":"Conditional"},{"origin":"Usa o teu cérebro","target":"Use your brain","tense":"Imperative"},{"origin":"Usa esta oportunidade","target":"Use this opportunity","tense":"Imperative"},{"origin":"Usem esta porta","target":"Use this door","tense":"Imperative"},{"origin":"Usem as instruções","target":"Use the instructions","tense":"Imperative"},{"origin":"Não uses isto","target":"Don't use this","tense":"Imperative"},{"origin":"Não usem o elevador","target":"Don't use the elevator","tense":"Imperative"},{"origin":"Eu costumava viver em Lisboa","target":"I used to live in Lisbon","tense":"Expressions"},{"origin":"Tu costumavas jogar futebol?","target":"Did you use to play football?","tense":"Expressions"},{"origin":"Ele costumava fumar","target":"He used to smoke","tense":"Expressions"},{"origin":"Ela costumava trabalhar aqui","target":"She used to work here","tense":"Expressions"},{"origin":"Nós costumávamos encontrar-nos todos os dias","target":"We used to meet every day","tense":"Expressions"},{"origin":"Eles costumavam ser amigos","target":"They used to be friends","tense":"Expressions"},{"origin":"Eu não uso redes sociais","target":"I don't use social media","tense":"Present"},{"origin":"Tu não usas a abordagem certa","target":"You don't use the right approach","tense":"Present"},{"origin":"Ele não usa violência","target":"He doesn't use violence","tense":"Present"},{"origin":"Ela não usa maquilhagem","target":"She doesn't use makeup","tense":"Present"},{"origin":"Nós não usamos plástico","target":"We don't use plastic","tense":"Present"},{"origin":"Eles não usam químicos","target":"They don't use chemicals","tense":"Present"},{"origin":"Eu não usei força","target":"I didn't use force","tense":"Past Simple"},{"origin":"Tu não usaste a oportunidade","target":"You didn't use the chance","tense":"Past Simple"},{"origin":"Ele não usou o meu nome","target":"He didn't use my name","tense":"Past Simple"},{"origin":"Ela não usou o manual","target":"She didn't use the manual","tense":"Past Simple"},{"origin":"Nós não usámos as palavras certas","target":"We didn't use the right words","tense":"Past Simple"},{"origin":"Eles não usaram armas","target":"They didn't use weapons","tense":"Past Simple"},{"origin":"O que é que tu usas para isto?","target":"What do you use for this?","tense":"Present"},{"origin":"Como é que tu usas isto?","target":"How do you use this?","tense":"Present"},{"origin":"Porque é que ele usa isto?","target":"Why does he use this?","tense":"Present"},{"origin":"Quando é que tu usaste isto?","target":"When did you use this?","tense":"Past Simple"},{"origin":"Onde é que eles usam isto?","target":"Where do they use this?","tense":"Present"},{"origin":"Quem está a usar o meu computador?","target":"Who is using my computer?","tense":"Present Continuous"},{"origin":"Eu estou habituado ao frio","target":"I am used to the cold","tense":"Expressions"},{"origin":"Tu estás habituado ao barulho","target":"You are used to the noise","tense":"Expressions"},{"origin":"Ele está habituado a levantar-se cedo","target":"He is used to getting up early","tense":"Expressions"},{"origin":"Ela está habituada a trabalhar sozinha","target":"She is used to working alone","tense":"Expressions"},{"origin":"Nós estamos habituados ao calor","target":"We are used to the heat","tense":"Expressions"},{"origin":"Eles estão habituados à pressão","target":"They are used to pressure","tense":"Expressions"},{"origin":"Eu estou a habituar-me ao novo trabalho","target":"I am getting used to the new job","tense":"Expressions"},{"origin":"Tu estás a habituar-te à casa nova","target":"You are getting used to the new house","tense":"Expressions"},{"origin":"Ele está a habituar-se à escola nova","target":"He is getting used to the new school","tense":"Expressions"},{"origin":"Ela está a habituar-se ao novo país","target":"She is getting used to the new country","tense":"Expressions"}],"de":[{"origin":"Ich benutze einen Computer","target":"I use a computer","tense":"Present"},{"origin":"Du benutzt mein Telefon","target":"You use my phone","tense":"Present"},{"origin":"Er benutzt das Internet","target":"He uses the Internet","tense":"Present"},{"origin":"Sie benutzt diese Methode","target":"She uses this method","tense":"Present"},{"origin":"Wir benutzen dieses Programm","target":"We use this program","tense":"Present"},{"origin":"Sie benutzen öffentliche Verkehrsmittel","target":"They use public transport","tense":"Present"},{"origin":"Ich benutzte deinen Stift","target":"I used your pen","tense":"Past Simple"},{"origin":"Du benutzt meine Idee","target":"You used my idea","tense":"Past Simple"},{"origin":"Er benutzte das falsche Werkzeug","target":"He used the wrong tool","tense":"Past Simple"},{"origin":"Sie benutzte eine Kreditkarte","target":"She used a credit card","tense":"Past Simple"},{"origin":"Wir benutzten alte Ausrüstung","target":"We used old equipment","tense":"Past Simple"},{"origin":"Sie benutzten alle Ressourcen","target":"They used all the resources","tense":"Past Simple"},{"origin":"Ich benutze gerade das Badezimmer","target":"I am using the bathroom now","tense":"Present Continuous"},{"origin":"Benutzt du mein Auto?","target":"Are you using my car?","tense":"Present Continuous"},{"origin":"Er benutzt eine neue Strategie","target":"He is using a new strategy","tense":"Present Continuous"},{"origin":"Sie benutzt meinen Computer","target":"She is using my computer","tense":"Present Continuous"},{"origin":"Wir benutzen ein neues System","target":"We are using a new system","tense":"Present Continuous"},{"origin":"Sie benutzen unsere Daten","target":"They are using our data","tense":"Present Continuous"},{"origin":"Ich benutzte den Drucker, als er kaputt ging","target":"I was using the printer when it broke","tense":"Past Continuous"},{"origin":"Benutzt du meinen Laptop?","target":"Were you using my laptop?","tense":"Past Continuous"},{"origin":"Er benutzte den ganzen Tag das Telefon","target":"He was using the phone all day","tense":"Past Continuous"},{"origin":"Sie benutzte diesen Raum","target":"She was using this room","tense":"Past Continuous"},{"origin":"Wir benutzten die alte Version","target":"We were using the old version","tense":"Past Continuous"},{"origin":"Sie benutzten unsere Ausrüstung","target":"They were using our equipment","tense":"Past Continuous"},{"origin":"Ich habe das nie benutzt","target":"I have never used this","tense":"Present Perfect"},{"origin":"Hast du die neue App schon benutzt?","target":"Have you used the new app yet?","tense":"Present Perfect"},{"origin":"Er hat diesen Trick schon mal benutzt","target":"He has used this trick before","tense":"Present Perfect"},{"origin":"Sie hat bereits alle Versuche benutzt","target":"She has already used all attempts","tense":"Present Perfect"},{"origin":"Wir haben diesen Ansatz viele Male benutzt","target":"We have used this approach many times","tense":"Present Perfect"},{"origin":"Sie haben das gesamte Budget verbraucht","target":"They have used the entire budget","tense":"Present Perfect"},{"origin":"Ich werde eine andere Methode benutzen","target":"I will use a different method","tense":"Future"},{"origin":"Wirst du mein Auto benutzen?","target":"Will you use my car?","tense":"Future"},{"origin":"Er wird diese Information benutzen","target":"He will use this information","tense":"Future"},{"origin":"Sie wird neue Technologie benutzen","target":"She will use new technology","tense":"Future"},{"origin":"Wir werden die besten Materialien verwenden","target":"We will use the best materials","tense":"Future"},{"origin":"Sie werden unseren Plan benutzen","target":"They will use our plan","tense":"Future"},{"origin":"Ich würde einen anderen Ansatz verwenden","target":"I would use a different approach","tense":"Conditional"},{"origin":"Würdest du das benutzen?","target":"Would you use this?","tense":"Conditional"},{"origin":"Er würde mehr Zeit verwenden","target":"He would use more time","tense":"Conditional"},{"origin":"Sie könnte etwas Hilfe gebrauchen","target":"She would use some help","tense":"Conditional"},{"origin":"Wir würden deinen Rat verwenden","target":"We would use your advice","tense":"Conditional"},{"origin":"Sie würden einen anderen Weg benutzen","target":"They would use another way","tense":"Conditional"},{"origin":"Benutze dein Gehirn","target":"Use your brain","tense":"Imperative"},{"origin":"Nutze diese Gelegenheit","target":"Use this opportunity","tense":"Imperative"},{"origin":"Benutzen Sie diese Tür","target":"Use this door","tense":"Imperative"},{"origin":"Benutzen Sie die Anleitung","target":"Use the instructions","tense":"Imperative"},{"origin":"Benutze das nicht","target":"Don't use this","tense":"Imperative"},{"origin":"Benutzen Sie nicht den Aufzug","target":"Don't use the elevator","tense":"Imperative"},{"origin":"Ich lebte früher in Berlin","target":"I used to live in Berlin","tense":"Expressions"},{"origin":"Hast du früher Fußball gespielt?","target":"Did you use to play football?","tense":"Expressions"},{"origin":"Er rauchte früher","target":"He used to smoke","tense":"Expressions"},{"origin":"Sie arbeitete früher hier","target":"She used to work here","tense":"Expressions"},{"origin":"Wir trafen uns früher jeden Tag","target":"We used to meet every day","tense":"Expressions"},{"origin":"Sie waren früher Freunde","target":"They used to be friends","tense":"Expressions"},{"origin":"Ich benutze keine sozialen Medien","target":"I don't use social media","tense":"Present"},{"origin":"Du benutzt nicht den richtigen Ansatz","target":"You don't use the right approach","tense":"Present"},{"origin":"Er wendet keine Gewalt an","target":"He doesn't use violence","tense":"Present"},{"origin":"Sie benutzt kein Make-up","target":"She doesn't use makeup","tense":"Present"},{"origin":"Wir benutzen kein Plastik","target":"We don't use plastic","tense":"Present"},{"origin":"Sie benutzen keine Chemikalien","target":"They don't use chemicals","tense":"Present"},{"origin":"Ich habe keine Gewalt angewendet","target":"I didn't use force","tense":"Past Simple"},{"origin":"Du hast die Chance nicht genutzt","target":"You didn't use the chance","tense":"Past Simple"},{"origin":"Er benutzte meinen Namen nicht","target":"He didn't use my name","tense":"Past Simple"},{"origin":"Sie benutzte das Handbuch nicht","target":"She didn't use the manual","tense":"Past Simple"},{"origin":"Wir benutzten nicht die richtigen Worte","target":"We didn't use the right words","tense":"Past Simple"},{"origin":"Sie benutzten keine Waffen","target":"They didn't use weapons","tense":"Past Simple"},{"origin":"Was benutzt du dafür?","target":"What do you use for this?","tense":"Present"},{"origin":"Wie benutzt du das?","target":"How do you use this?","tense":"Present"},{"origin":"Warum benutzt er das?","target":"Why does he use this?","tense":"Present"},{"origin":"Wann hast du das benutzt?","target":"When did you use this?","tense":"Past Simple"},{"origin":"Wo benutzen sie das?","target":"Where do they use this?","tense":"Present"},{"origin":"Wer benutzt meinen Computer?","target":"Who is using my computer?","tense":"Present Continuous"},{"origin":"Ich bin an die Kälte gewöhnt","target":"I am used to the cold","tense":"Expressions"},{"origin":"Du bist an den Lärm gewöhnt","target":"You are used to the noise","tense":"Expressions"},{"origin":"Er ist daran gewöhnt, früh aufzustehen","target":"He is used to getting up early","tense":"Expressions"},{"origin":"Sie ist daran gewöhnt, alleine zu arbeiten","target":"She is used to working alone","tense":"Expressions"},{"origin":"Wir sind an die Hitze gewöhnt","target":"We are used to the heat","tense":"Expressions"},{"origin":"Sie sind an Druck gewöhnt","target":"They are used to pressure","tense":"Expressions"},{"origin":"Ich gewöhne mich an den neuen Job","target":"I am getting used to the new job","tense":"Expressions"},{"origin":"Du gewöhnst dich an das neue Haus","target":"You are getting used to the new house","tense":"Expressions"},{"origin":"Er gewöhnt sich an die neue Schule","target":"He is getting used to the new school","tense":"Expressions"},{"origin":"Sie gewöhnt sich an das neue Land","target":"She is getting used to the new country","tense":"Expressions"}],"fr":[{"origin":"J'utilise un ordinateur","target":"I use a computer","tense":"Present"},{"origin":"Tu utilises mon téléphone","target":"You use my phone","tense":"Present"},{"origin":"Il utilise Internet","target":"He uses the Internet","tense":"Present"},{"origin":"Elle utilise cette méthode","target":"She uses this method","tense":"Present"},{"origin":"Nous utilisons ce programme","target":"We use this program","tense":"Present"},{"origin":"Ils utilisent les transports en commun","target":"They use public transport","tense":"Present"},{"origin":"J'ai utilisé ton stylo","target":"I used your pen","tense":"Past Simple"},{"origin":"Tu as utilisé mon idée","target":"You used my idea","tense":"Past Simple"},{"origin":"Il a utilisé le mauvais outil","target":"He used the wrong tool","tense":"Past Simple"},{"origin":"Elle a utilisé une carte de crédit","target":"She used a credit card","tense":"Past Simple"},{"origin":"Nous avons utilisé du vieux matériel","target":"We used old equipment","tense":"Past Simple"},{"origin":"Ils ont utilisé toutes les ressources","target":"They used all the resources","tense":"Past Simple"},{"origin":"J'utilise les toilettes maintenant","target":"I am using the bathroom now","tense":"Present Continuous"},{"origin":"Tu utilises ma voiture?","target":"Are you using my car?","tense":"Present Continuous"},{"origin":"Il utilise une nouvelle stratégie","target":"He is using a new strategy","tense":"Present Continuous"},{"origin":"Elle utilise mon ordinateur","target":"She is using my computer","tense":"Present Continuous"},{"origin":"Nous utilisons un nouveau système","target":"We are using a new system","tense":"Present Continuous"},{"origin":"Ils utilisent nos données","target":"They are using our data","tense":"Present Continuous"},{"origin":"J'utilisais l'imprimante quand elle s'est cassée","target":"I was using the printer when it broke","tense":"Past Continuous"},{"origin":"Tu utilisais mon portable?","target":"Were you using my laptop?","tense":"Past Continuous"},{"origin":"Il utilisait le téléphone toute la journée","target":"He was using the phone all day","tense":"Past Continuous"},{"origin":"Elle utilisait cette pièce","target":"She was using this room","tense":"Past Continuous"},{"origin":"Nous utilisions l'ancienne version","target":"We were using the old version","tense":"Past Continuous"},{"origin":"Ils utilisaient notre équipement","target":"They were using our equipment","tense":"Past Continuous"},{"origin":"Je n'ai jamais utilisé ça","target":"I have never used this","tense":"Present Perfect"},{"origin":"As-tu déjà utilisé la nouvelle application?","target":"Have you used the new app yet?","tense":"Present Perfect"},{"origin":"Il a déjà utilisé cette astuce","target":"He has used this trick before","tense":"Present Perfect"},{"origin":"Elle a déjà utilisé toutes les tentatives","target":"She has already used all attempts","tense":"Present Perfect"},{"origin":"Nous avons utilisé cette approche plusieurs fois","target":"We have used this approach many times","tense":"Present Perfect"},{"origin":"Ils ont utilisé tout le budget","target":"They have used the entire budget","tense":"Present Perfect"},{"origin":"J'utiliserai une méthode différente","target":"I will use a different method","tense":"Future"},{"origin":"Tu utiliseras ma voiture?","target":"Will you use my car?","tense":"Future"},{"origin":"Il utilisera cette information","target":"He will use this information","tense":"Future"},{"origin":"Elle utilisera une nouvelle technologie","target":"She will use new technology","tense":"Future"},{"origin":"Nous utiliserons les meilleurs matériaux","target":"We will use the best materials","tense":"Future"},{"origin":"Ils utiliseront notre plan","target":"They will use our plan","tense":"Future"},{"origin":"J'utiliserais une approche différente","target":"I would use a different approach","tense":"Conditional"},{"origin":"Tu utiliserais ça?","target":"Would you use this?","tense":"Conditional"},{"origin":"Il utiliserait plus de temps","target":"He would use more time","tense":"Conditional"},{"origin":"Elle aurait besoin d'aide","target":"She would use some help","tense":"Conditional"},{"origin":"Nous utiliserions ton conseil","target":"We would use your advice","tense":"Conditional"},{"origin":"Ils utiliseraient une autre façon","target":"They would use another way","tense":"Conditional"},{"origin":"Utilise ton cerveau","target":"Use your brain","tense":"Imperative"},{"origin":"Utilise cette opportunité","target":"Use this opportunity","tense":"Imperative"},{"origin":"Utilisez cette porte","target":"Use this door","tense":"Imperative"},{"origin":"Utilisez les instructions","target":"Use the instructions","tense":"Imperative"},{"origin":"N'utilise pas ça","target":"Don't use this","tense":"Imperative"},{"origin":"N'utilisez pas l'ascenseur","target":"Don't use the elevator","tense":"Imperative"},{"origin":"Je vivais à Paris avant","target":"I used to live in Paris","tense":"Expressions"},{"origin":"Tu jouais au football avant?","target":"Did you use to play football?","tense":"Expressions"},{"origin":"Il fumait avant","target":"He used to smoke","tense":"Expressions"},{"origin":"Elle travaillait ici avant","target":"She used to work here","tense":"Expressions"},{"origin":"Nous nous rencontrions tous les jours avant","target":"We used to meet every day","tense":"Expressions"},{"origin":"Ils étaient amis avant","target":"They used to be friends","tense":"Expressions"},{"origin":"Je n'utilise pas les réseaux sociaux","target":"I don't use social media","tense":"Present"},{"origin":"Tu n'utilises pas la bonne approche","target":"You don't use the right approach","tense":"Present"},{"origin":"Il n'utilise pas la violence","target":"He doesn't use violence","tense":"Present"},{"origin":"Elle n'utilise pas de maquillage","target":"She doesn't use makeup","tense":"Present"},{"origin":"Nous n'utilisons pas de plastique","target":"We don't use plastic","tense":"Present"},{"origin":"Ils n'utilisent pas de produits chimiques","target":"They don't use chemicals","tense":"Present"},{"origin":"Je n'ai pas utilisé la force","target":"I didn't use force","tense":"Past Simple"},{"origin":"Tu n'as pas saisi la chance","target":"You didn't use the chance","tense":"Past Simple"},{"origin":"Il n'a pas utilisé mon nom","target":"He didn't use my name","tense":"Past Simple"},{"origin":"Elle n'a pas utilisé le manuel","target":"She didn't use the manual","tense":"Past Simple"},{"origin":"Nous n'avons pas utilisé les bons mots","target":"We didn't use the right words","tense":"Past Simple"},{"origin":"Ils n'ont pas utilisé d'armes","target":"They didn't use weapons","tense":"Past Simple"},{"origin":"Qu'utilises-tu pour ça?","target":"What do you use for this?","tense":"Present"},{"origin":"Comment utilises-tu ça?","target":"How do you use this?","tense":"Present"},{"origin":"Pourquoi utilise-t-il ça?","target":"Why does he use this?","tense":"Present"},{"origin":"Quand as-tu utilisé ça?","target":"When did you use this?","tense":"Past Simple"},{"origin":"Où utilisent-ils ça?","target":"Where do they use this?","tense":"Present"},{"origin":"Qui utilise mon ordinateur?","target":"Who is using my computer?","tense":"Present Continuous"},{"origin":"Je suis habitué au froid","target":"I am used to the cold","tense":"Expressions"},{"origin":"Tu es habitué au bruit","target":"You are used to the noise","tense":"Expressions"},{"origin":"Il est habitué à se lever tôt","target":"He is used to getting up early","tense":"Expressions"},{"origin":"Elle est habituée à travailler seule","target":"She is used to working alone","tense":"Expressions"},{"origin":"Nous sommes habitués à la chaleur","target":"We are used to the heat","tense":"Expressions"},{"origin":"Ils sont habitués à la pression","target":"They are used to pressure","tense":"Expressions"},{"origin":"Je m'habitue au nouveau travail","target":"I am getting used to the new job","tense":"Expressions"},{"origin":"Tu t'habitues à la nouvelle maison","target":"You are getting used to the new house","tense":"Expressions"},{"origin":"Il s'habitue à la nouvelle école","target":"He is getting used to the new school","tense":"Expressions"},{"origin":"Elle s'habitue au nouveau pays","target":"She is getting used to the new country","tense":"Expressions"}]}}